{"schema_version":3,"dataset_id":"who_homicide_0_14_national_query_v2_2","country":{"code":"2460","name_source":"Uruguay"},"coverage":{"year_min":1997,"year_max":2023,"record_count":58,"sexes":["female","male","unknown"],"by_sex":{"female":{"year_min":1997,"year_max":2023,"record_count":26,"years":[1997,1998,1999,2000,2001,2002,2003,2004,2005,2006,2007,2008,2009,2010,2012,2013,2014,2015,2016,2017,2018,2019,2020,2021,2022,2023]},"male":{"year_min":1997,"year_max":2023,"record_count":26,"years":[1997,1998,1999,2000,2001,2002,2003,2004,2005,2006,2007,2008,2009,2010,2012,2013,2014,2015,2016,2017,2018,2019,2020,2021,2022,2023]},"unknown":{"year_min":1998,"year_max":2021,"record_count":6,"years":[1998,2004,2014,2016,2017,2021]}}},"records":[{"record_id":"who-mdb-014-9ea590ad11933aaa5866e4d8","year":1997,"sex_code":"female","death_count":6,"source_version":"WHO-MDB-ICD10-fc047e2e14694956","retrieved_at":"2026-07-22T16:07:26.508035+00:00","audit_version":"who_mortality_v1_2_2"},{"record_id":"who-mdb-014-d5910c0bb0c6251df1edf304","year":1997,"sex_code":"male","death_count":6,"source_version":"WHO-MDB-ICD10-fc047e2e14694956","retrieved_at":"2026-07-22T16:07:26.508035+00:00","audit_version":"who_mortality_v1_2_2"},{"record_id":"who-mdb-014-3f47c3a794206a5d00a4f99b","year":1998,"sex_code":"female","death_count":1,"source_version":"WHO-MDB-ICD10-fc047e2e14694956","retrieved_at":"2026-07-22T16:07:26.508035+00:00","audit_version":"who_mortality_v1_2_2"},{"record_id":"who-mdb-014-dda40f078a7c06038907e456","year":1998,"sex_code":"male","death_count":4,"source_version":"WHO-MDB-ICD10-fc047e2e14694956","retrieved_at":"2026-07-22T16:07:26.508035+00:00","audit_version":"who_mortality_v1_2_2"},{"record_id":"who-mdb-014-065e4ada3843837db973ce97","year":1998,"sex_code":"unknown","death_count":0,"source_version":"WHO-MDB-ICD10-fc047e2e14694956","retrieved_at":"2026-07-22T16:07:26.508035+00:00","audit_version":"who_mortality_v1_2_2"},{"record_id":"who-mdb-014-0991670130b2fa8075eef79d","year":1999,"sex_code":"female","death_count":4,"source_version":"WHO-MDB-ICD10-fc047e2e14694956","retrieved_at":"2026-07-22T16:07:26.508035+00:00","audit_version":"who_mortality_v1_2_2"},{"record_id":"who-mdb-014-159be4f8789e50085a3ade6e","year":1999,"sex_code":"male","death_count":2,"source_version":"WHO-MDB-ICD10-fc047e2e14694956","retrieved_at":"2026-07-22T16:07:26.508035+00:00","audit_version":"who_mortality_v1_2_2"},{"record_id":"who-mdb-014-8500ec810891657d6bae2851","year":2000,"sex_code":"female","death_count":2,"source_version":"WHO-MDB-ICD10-fc047e2e14694956","retrieved_at":"2026-07-22T16:07:26.508035+00:00","audit_version":"who_mortality_v1_2_2"},{"record_id":"who-mdb-014-c1e9cefd65d118b22d2263df","year":2000,"sex_code":"male","death_count":9,"source_version":"WHO-MDB-ICD10-fc047e2e14694956","retrieved_at":"2026-07-22T16:07:26.508035+00:00","audit_version":"who_mortality_v1_2_2"},{"record_id":"who-mdb-014-ce3b6bc1959c197945a8e62f","year":2001,"sex_code":"female","death_count":5,"source_version":"WHO-MDB-ICD10-fc047e2e14694956","retrieved_at":"2026-07-22T16:07:26.508035+00:00","audit_version":"who_mortality_v1_2_2"},{"record_id":"who-mdb-014-b5a835c558dfafc0d7bf52ae","year":2001,"sex_code":"male","death_count":5,"source_version":"WHO-MDB-ICD10-fc047e2e14694956","retrieved_at":"2026-07-22T16:07:26.508035+00:00","audit_version":"who_mortality_v1_2_2"},{"record_id":"who-mdb-014-e299a2c2bdeb08a76119177b","year":2002,"sex_code":"female","death_count":1,"source_version":"WHO-MDB-ICD10-fc047e2e14694956","retrieved_at":"2026-07-22T16:07:26.508035+00:00","audit_version":"who_mortality_v1_2_2"},{"record_id":"who-mdb-014-d891a36a0a9e83fa2f755ce7","year":2002,"sex_code":"male","death_count":6,"source_version":"WHO-MDB-ICD10-fc047e2e14694956","retrieved_at":"2026-07-22T16:07:26.508035+00:00","audit_version":"who_mortality_v1_2_2"},{"record_id":"who-mdb-014-5c19bed32f4c36eeca4c6501","year":2003,"sex_code":"female","death_count":5,"source_version":"WHO-MDB-ICD10-fc047e2e14694956","retrieved_at":"2026-07-22T16:07:26.508035+00:00","audit_version":"who_mortality_v1_2_2"},{"record_id":"who-mdb-014-cae9fede756040bd5039fce5","year":2003,"sex_code":"male","death_count":4,"source_version":"WHO-MDB-ICD10-fc047e2e14694956","retrieved_at":"2026-07-22T16:07:26.508035+00:00","audit_version":"who_mortality_v1_2_2"},{"record_id":"who-mdb-014-72601678033dd2e3ec47acf7","year":2004,"sex_code":"female","death_count":8,"source_version":"WHO-MDB-ICD10-fc047e2e14694956","retrieved_at":"2026-07-22T16:07:26.508035+00:00","audit_version":"who_mortality_v1_2_2"},{"record_id":"who-mdb-014-09eb9b205db6e0c45f40190f","year":2004,"sex_code":"male","death_count":3,"source_version":"WHO-MDB-ICD10-fc047e2e14694956","retrieved_at":"2026-07-22T16:07:26.508035+00:00","audit_version":"who_mortality_v1_2_2"},{"record_id":"who-mdb-014-5c55a93b2d9404644c3d59b8","year":2004,"sex_code":"unknown","death_count":0,"source_version":"WHO-MDB-ICD10-fc047e2e14694956","retrieved_at":"2026-07-22T16:07:26.508035+00:00","audit_version":"who_mortality_v1_2_2"},{"record_id":"who-mdb-014-71d54707f68d3768b4babd4c","year":2005,"sex_code":"female","death_count":2,"source_version":"WHO-MDB-ICD10-fc047e2e14694956","retrieved_at":"2026-07-22T16:07:26.508035+00:00","audit_version":"who_mortality_v1_2_2"},{"record_id":"who-mdb-014-a360e37a51c394af6638e464","year":2005,"sex_code":"male","death_count":5,"source_version":"WHO-MDB-ICD10-fc047e2e14694956","retrieved_at":"2026-07-22T16:07:26.508035+00:00","audit_version":"who_mortality_v1_2_2"},{"record_id":"who-mdb-014-259654723537112d93ba4a4f","year":2006,"sex_code":"female","death_count":2,"source_version":"WHO-MDB-ICD10-fc047e2e14694956","retrieved_at":"2026-07-22T16:07:26.508035+00:00","audit_version":"who_mortality_v1_2_2"},{"record_id":"who-mdb-014-922e8c7db143a1b7b9aa84ad","year":2006,"sex_code":"male","death_count":1,"source_version":"WHO-MDB-ICD10-fc047e2e14694956","retrieved_at":"2026-07-22T16:07:26.508035+00:00","audit_version":"who_mortality_v1_2_2"},{"record_id":"who-mdb-014-387392b74a639c8bf881be5d","year":2007,"sex_code":"female","death_count":2,"source_version":"WHO-MDB-ICD10-fc047e2e14694956","retrieved_at":"2026-07-22T16:07:26.508035+00:00","audit_version":"who_mortality_v1_2_2"},{"record_id":"who-mdb-014-c197e8d46903129ffcf79472","year":2007,"sex_code":"male","death_count":5,"source_version":"WHO-MDB-ICD10-fc047e2e14694956","retrieved_at":"2026-07-22T16:07:26.508035+00:00","audit_version":"who_mortality_v1_2_2"},{"record_id":"who-mdb-014-f616fa4ddbe807870b42d1e2","year":2008,"sex_code":"female","death_count":9,"source_version":"WHO-MDB-ICD10-fc047e2e14694956","retrieved_at":"2026-07-22T16:07:26.508035+00:00","audit_version":"who_mortality_v1_2_2"},{"record_id":"who-mdb-014-24479e6db1fe0413891801c2","year":2008,"sex_code":"male","death_count":3,"source_version":"WHO-MDB-ICD10-fc047e2e14694956","retrieved_at":"2026-07-22T16:07:26.508035+00:00","audit_version":"who_mortality_v1_2_2"},{"record_id":"who-mdb-014-5d60f6c5b545951edac9f4f3","year":2009,"sex_code":"female","death_count":1,"source_version":"WHO-MDB-ICD10-fc047e2e14694956","retrieved_at":"2026-07-22T16:07:26.508035+00:00","audit_version":"who_mortality_v1_2_2"},{"record_id":"who-mdb-014-5bcfab4585946c56ab2df7ec","year":2009,"sex_code":"male","death_count":3,"source_version":"WHO-MDB-ICD10-fc047e2e14694956","retrieved_at":"2026-07-22T16:07:26.508035+00:00","audit_version":"who_mortality_v1_2_2"},{"record_id":"who-mdb-014-40a9ab3e7bc6e3288fa151ca","year":2010,"sex_code":"female","death_count":5,"source_version":"WHO-MDB-ICD10-fc047e2e14694956","retrieved_at":"2026-07-22T16:07:26.508035+00:00","audit_version":"who_mortality_v1_2_2"},{"record_id":"who-mdb-014-2bc698c1d28940e3586f38d0","year":2010,"sex_code":"male","death_count":1,"source_version":"WHO-MDB-ICD10-fc047e2e14694956","retrieved_at":"2026-07-22T16:07:26.508035+00:00","audit_version":"who_mortality_v1_2_2"},{"record_id":"who-mdb-014-3f92a67a4c02c8933718630c","year":2012,"sex_code":"female","death_count":2,"source_version":"WHO-MDB-ICD10-fc047e2e14694956","retrieved_at":"2026-07-22T16:07:26.508035+00:00","audit_version":"who_mortality_v1_2_2"},{"record_id":"who-mdb-014-04437ee18940f9aed0a79e79","year":2012,"sex_code":"male","death_count":4,"source_version":"WHO-MDB-ICD10-fc047e2e14694956","retrieved_at":"2026-07-22T16:07:26.508035+00:00","audit_version":"who_mortality_v1_2_2"},{"record_id":"who-mdb-014-62d6d2dd0f446e96192e8378","year":2013,"sex_code":"female","death_count":0,"source_version":"WHO-MDB-ICD10-fc047e2e14694956","retrieved_at":"2026-07-22T16:07:26.508035+00:00","audit_version":"who_mortality_v1_2_2"},{"record_id":"who-mdb-014-40b4e5dc11181ab9c39845fe","year":2013,"sex_code":"male","death_count":3,"source_version":"WHO-MDB-ICD10-fc047e2e14694956","retrieved_at":"2026-07-22T16:07:26.508035+00:00","audit_version":"who_mortality_v1_2_2"},{"record_id":"who-mdb-014-7cf769edb49ea025261af9a6","year":2014,"sex_code":"female","death_count":2,"source_version":"WHO-MDB-ICD10-fc047e2e14694956","retrieved_at":"2026-07-22T16:07:26.508035+00:00","audit_version":"who_mortality_v1_2_2"},{"record_id":"who-mdb-014-76d5bd0eac64592c854be761","year":2014,"sex_code":"male","death_count":1,"source_version":"WHO-MDB-ICD10-fc047e2e14694956","retrieved_at":"2026-07-22T16:07:26.508035+00:00","audit_version":"who_mortality_v1_2_2"},{"record_id":"who-mdb-014-93d324304b3ce693302f3037","year":2014,"sex_code":"unknown","death_count":0,"source_version":"WHO-MDB-ICD10-fc047e2e14694956","retrieved_at":"2026-07-22T16:07:26.508035+00:00","audit_version":"who_mortality_v1_2_2"},{"record_id":"who-mdb-014-a5d2c2f288eca3261f10f208","year":2015,"sex_code":"female","death_count":0,"source_version":"WHO-MDB-ICD10-fc047e2e14694956","retrieved_at":"2026-07-22T16:07:26.508035+00:00","audit_version":"who_mortality_v1_2_2"},{"record_id":"who-mdb-014-af0e7798f90dd54d51fc9773","year":2015,"sex_code":"male","death_count":0,"source_version":"WHO-MDB-ICD10-fc047e2e14694956","retrieved_at":"2026-07-22T16:07:26.508035+00:00","audit_version":"who_mortality_v1_2_2"},{"record_id":"who-mdb-014-c91acd48b037741ba6282d8d","year":2016,"sex_code":"female","death_count":3,"source_version":"WHO-MDB-ICD10-fc047e2e14694956","retrieved_at":"2026-07-22T16:07:26.508035+00:00","audit_version":"who_mortality_v1_2_2"},{"record_id":"who-mdb-014-748e790a4c72a2279530617d","year":2016,"sex_code":"male","death_count":2,"source_version":"WHO-MDB-ICD10-fc047e2e14694956","retrieved_at":"2026-07-22T16:07:26.508035+00:00","audit_version":"who_mortality_v1_2_2"},{"record_id":"who-mdb-014-d5f40df721aed981e0001bf2","year":2016,"sex_code":"unknown","death_count":1,"source_version":"WHO-MDB-ICD10-fc047e2e14694956","retrieved_at":"2026-07-22T16:07:26.508035+00:00","audit_version":"who_mortality_v1_2_2"},{"record_id":"who-mdb-014-1877ef861a188f23b322102d","year":2017,"sex_code":"female","death_count":3,"source_version":"WHO-MDB-ICD10-fc047e2e14694956","retrieved_at":"2026-07-22T16:07:26.508035+00:00","audit_version":"who_mortality_v1_2_2"},{"record_id":"who-mdb-014-7fb9ebf51dc13ee31f3e08f8","year":2017,"sex_code":"male","death_count":4,"source_version":"WHO-MDB-ICD10-fc047e2e14694956","retrieved_at":"2026-07-22T16:07:26.508035+00:00","audit_version":"who_mortality_v1_2_2"},{"record_id":"who-mdb-014-27f1d407746cb4eb02924872","year":2017,"sex_code":"unknown","death_count":1,"source_version":"WHO-MDB-ICD10-fc047e2e14694956","retrieved_at":"2026-07-22T16:07:26.508035+00:00","audit_version":"who_mortality_v1_2_2"},{"record_id":"who-mdb-014-09a10814238e1c1453c201b3","year":2018,"sex_code":"female","death_count":3,"source_version":"WHO-MDB-ICD10-fc047e2e14694956","retrieved_at":"2026-07-22T16:07:26.508035+00:00","audit_version":"who_mortality_v1_2_2"},{"record_id":"who-mdb-014-e9c56e1b5d7fc4b8382c424b","year":2018,"sex_code":"male","death_count":4,"source_version":"WHO-MDB-ICD10-fc047e2e14694956","retrieved_at":"2026-07-22T16:07:26.508035+00:00","audit_version":"who_mortality_v1_2_2"},{"record_id":"who-mdb-014-93ad2bc6e91c7345e7d404d5","year":2019,"sex_code":"female","death_count":2,"source_version":"WHO-MDB-ICD10-fc047e2e14694956","retrieved_at":"2026-07-22T16:07:26.508035+00:00","audit_version":"who_mortality_v1_2_2"},{"record_id":"who-mdb-014-01aadfc33180a997eaa068fc","year":2019,"sex_code":"male","death_count":7,"source_version":"WHO-MDB-ICD10-fc047e2e14694956","retrieved_at":"2026-07-22T16:07:26.508035+00:00","audit_version":"who_mortality_v1_2_2"},{"record_id":"who-mdb-014-9fe9bad2b30d02f35336ecb9","year":2020,"sex_code":"female","death_count":4,"source_version":"WHO-MDB-ICD10-fc047e2e14694956","retrieved_at":"2026-07-22T16:07:26.508035+00:00","audit_version":"who_mortality_v1_2_2"},{"record_id":"who-mdb-014-4e6163487f287b2433285b27","year":2020,"sex_code":"male","death_count":5,"source_version":"WHO-MDB-ICD10-fc047e2e14694956","retrieved_at":"2026-07-22T16:07:26.508035+00:00","audit_version":"who_mortality_v1_2_2"},{"record_id":"who-mdb-014-3525c433447b85569f29ea7a","year":2021,"sex_code":"female","death_count":2,"source_version":"WHO-MDB-ICD10-fc047e2e14694956","retrieved_at":"2026-07-22T16:07:26.508035+00:00","audit_version":"who_mortality_v1_2_2"},{"record_id":"who-mdb-014-ce61a5239a5b0b9ec78822c7","year":2021,"sex_code":"male","death_count":1,"source_version":"WHO-MDB-ICD10-fc047e2e14694956","retrieved_at":"2026-07-22T16:07:26.508035+00:00","audit_version":"who_mortality_v1_2_2"},{"record_id":"who-mdb-014-ed75757778e2a7c2ccc4491e","year":2021,"sex_code":"unknown","death_count":0,"source_version":"WHO-MDB-ICD10-fc047e2e14694956","retrieved_at":"2026-07-22T16:07:26.508035+00:00","audit_version":"who_mortality_v1_2_2"},{"record_id":"who-mdb-014-385200ac0f875750ffbabe13","year":2022,"sex_code":"female","death_count":3,"source_version":"WHO-MDB-ICD10-fc047e2e14694956","retrieved_at":"2026-07-22T16:07:26.508035+00:00","audit_version":"who_mortality_v1_2_2"},{"record_id":"who-mdb-014-b2eabfd8055d240b10f7481d","year":2022,"sex_code":"male","death_count":3,"source_version":"WHO-MDB-ICD10-fc047e2e14694956","retrieved_at":"2026-07-22T16:07:26.508035+00:00","audit_version":"who_mortality_v1_2_2"},{"record_id":"who-mdb-014-d090add5377d95ae8cfbd121","year":2023,"sex_code":"female","death_count":2,"source_version":"WHO-MDB-ICD10-fc047e2e14694956","retrieved_at":"2026-07-22T16:07:26.508035+00:00","audit_version":"who_mortality_v1_2_2"},{"record_id":"who-mdb-014-8f1e4e3b87a8f7d9893c3b2a","year":2023,"sex_code":"male","death_count":4,"source_version":"WHO-MDB-ICD10-fc047e2e14694956","retrieved_at":"2026-07-22T16:07:26.508035+00:00","audit_version":"who_mortality_v1_2_2"}],"constraints":{"national_only":true,"age_scope":"under_15_partial","strict_under_18":false,"sex_aggregation":true,"source_records_sex_aggregation":false,"both_sexes_displayed_separately":true,"integrated_female_male_total":true,"integrated_total_requires_both_components":true,"integrated_total_includes_unknown":false,"unknown_sex_exposed_in_interface":false,"world_total":false,"missing_years_are_zero":false,"cross_country_comparison":true,"cross_country_sums":false,"population_rates":false}}