{"schema_version":3,"dataset_id":"who_homicide_0_14_national_query_v2_2","country":{"code":"4302","name_source":"Turkmenistan"},"coverage":{"year_min":1999,"year_max":2015,"record_count":34,"sexes":["female","male"],"by_sex":{"female":{"year_min":1999,"year_max":2015,"record_count":17,"years":[1999,2000,2001,2002,2003,2004,2005,2006,2007,2008,2009,2010,2011,2012,2013,2014,2015]},"male":{"year_min":1999,"year_max":2015,"record_count":17,"years":[1999,2000,2001,2002,2003,2004,2005,2006,2007,2008,2009,2010,2011,2012,2013,2014,2015]}}},"records":[{"record_id":"who-mdb-014-feba2e30755a83029b25fe16","year":1999,"sex_code":"female","death_count":6,"source_version":"WHO-MDB-ICD10-fc047e2e14694956","retrieved_at":"2026-07-22T16:07:26.508035+00:00","audit_version":"who_mortality_v1_2_2"},{"record_id":"who-mdb-014-ed520ebdb1ccc8ba7ceb994c","year":1999,"sex_code":"male","death_count":4,"source_version":"WHO-MDB-ICD10-fc047e2e14694956","retrieved_at":"2026-07-22T16:07:26.508035+00:00","audit_version":"who_mortality_v1_2_2"},{"record_id":"who-mdb-014-9ec46c6368fc18a2ad72bcb9","year":2000,"sex_code":"female","death_count":1,"source_version":"WHO-MDB-ICD10-fc047e2e14694956","retrieved_at":"2026-07-22T16:07:26.508035+00:00","audit_version":"who_mortality_v1_2_2"},{"record_id":"who-mdb-014-5c454a9a519604c5b0adfff9","year":2000,"sex_code":"male","death_count":4,"source_version":"WHO-MDB-ICD10-fc047e2e14694956","retrieved_at":"2026-07-22T16:07:26.508035+00:00","audit_version":"who_mortality_v1_2_2"},{"record_id":"who-mdb-014-d6421aa958f2c9b76e61dacd","year":2001,"sex_code":"female","death_count":1,"source_version":"WHO-MDB-ICD10-fc047e2e14694956","retrieved_at":"2026-07-22T16:07:26.508035+00:00","audit_version":"who_mortality_v1_2_2"},{"record_id":"who-mdb-014-0085358235afa4fafea8197f","year":2001,"sex_code":"male","death_count":5,"source_version":"WHO-MDB-ICD10-fc047e2e14694956","retrieved_at":"2026-07-22T16:07:26.508035+00:00","audit_version":"who_mortality_v1_2_2"},{"record_id":"who-mdb-014-7f307ebd52c2116d533a995a","year":2002,"sex_code":"female","death_count":2,"source_version":"WHO-MDB-ICD10-fc047e2e14694956","retrieved_at":"2026-07-22T16:07:26.508035+00:00","audit_version":"who_mortality_v1_2_2"},{"record_id":"who-mdb-014-607961c027ea66a9f2d84734","year":2002,"sex_code":"male","death_count":5,"source_version":"WHO-MDB-ICD10-fc047e2e14694956","retrieved_at":"2026-07-22T16:07:26.508035+00:00","audit_version":"who_mortality_v1_2_2"},{"record_id":"who-mdb-014-43df0859f2c172366893eb89","year":2003,"sex_code":"female","death_count":1,"source_version":"WHO-MDB-ICD10-fc047e2e14694956","retrieved_at":"2026-07-22T16:07:26.508035+00:00","audit_version":"who_mortality_v1_2_2"},{"record_id":"who-mdb-014-04da94ec0359ca5fe3a4a4c4","year":2003,"sex_code":"male","death_count":2,"source_version":"WHO-MDB-ICD10-fc047e2e14694956","retrieved_at":"2026-07-22T16:07:26.508035+00:00","audit_version":"who_mortality_v1_2_2"},{"record_id":"who-mdb-014-42a7af0494dcdf0613376de9","year":2004,"sex_code":"female","death_count":1,"source_version":"WHO-MDB-ICD10-fc047e2e14694956","retrieved_at":"2026-07-22T16:07:26.508035+00:00","audit_version":"who_mortality_v1_2_2"},{"record_id":"who-mdb-014-a6a7d8aa8d2ed171d5b4033d","year":2004,"sex_code":"male","death_count":1,"source_version":"WHO-MDB-ICD10-fc047e2e14694956","retrieved_at":"2026-07-22T16:07:26.508035+00:00","audit_version":"who_mortality_v1_2_2"},{"record_id":"who-mdb-014-726a71c4998bdba2f53090f7","year":2005,"sex_code":"female","death_count":0,"source_version":"WHO-MDB-ICD10-fc047e2e14694956","retrieved_at":"2026-07-22T16:07:26.508035+00:00","audit_version":"who_mortality_v1_2_2"},{"record_id":"who-mdb-014-a1728118afe009d234ec1a03","year":2005,"sex_code":"male","death_count":2,"source_version":"WHO-MDB-ICD10-fc047e2e14694956","retrieved_at":"2026-07-22T16:07:26.508035+00:00","audit_version":"who_mortality_v1_2_2"},{"record_id":"who-mdb-014-0e1947ba5969a7b52c66f955","year":2006,"sex_code":"female","death_count":1,"source_version":"WHO-MDB-ICD10-fc047e2e14694956","retrieved_at":"2026-07-22T16:07:26.508035+00:00","audit_version":"who_mortality_v1_2_2"},{"record_id":"who-mdb-014-1277baa3da46ac3bc7225efb","year":2006,"sex_code":"male","death_count":1,"source_version":"WHO-MDB-ICD10-fc047e2e14694956","retrieved_at":"2026-07-22T16:07:26.508035+00:00","audit_version":"who_mortality_v1_2_2"},{"record_id":"who-mdb-014-b9426ee64b678eb2aa99321f","year":2007,"sex_code":"female","death_count":0,"source_version":"WHO-MDB-ICD10-fc047e2e14694956","retrieved_at":"2026-07-22T16:07:26.508035+00:00","audit_version":"who_mortality_v1_2_2"},{"record_id":"who-mdb-014-6e4ec2671b71e175c6baf932","year":2007,"sex_code":"male","death_count":1,"source_version":"WHO-MDB-ICD10-fc047e2e14694956","retrieved_at":"2026-07-22T16:07:26.508035+00:00","audit_version":"who_mortality_v1_2_2"},{"record_id":"who-mdb-014-169fb22a94883069e2ebea09","year":2008,"sex_code":"female","death_count":0,"source_version":"WHO-MDB-ICD10-fc047e2e14694956","retrieved_at":"2026-07-22T16:07:26.508035+00:00","audit_version":"who_mortality_v1_2_2"},{"record_id":"who-mdb-014-fbefa9092366993bd1984835","year":2008,"sex_code":"male","death_count":0,"source_version":"WHO-MDB-ICD10-fc047e2e14694956","retrieved_at":"2026-07-22T16:07:26.508035+00:00","audit_version":"who_mortality_v1_2_2"},{"record_id":"who-mdb-014-c1d59f5f513963f9c0d02c44","year":2009,"sex_code":"female","death_count":2,"source_version":"WHO-MDB-ICD10-fc047e2e14694956","retrieved_at":"2026-07-22T16:07:26.508035+00:00","audit_version":"who_mortality_v1_2_2"},{"record_id":"who-mdb-014-5e7aee0e3b7123d88289114d","year":2009,"sex_code":"male","death_count":4,"source_version":"WHO-MDB-ICD10-fc047e2e14694956","retrieved_at":"2026-07-22T16:07:26.508035+00:00","audit_version":"who_mortality_v1_2_2"},{"record_id":"who-mdb-014-b7d3fbd89ae79fa7ad01cc7f","year":2010,"sex_code":"female","death_count":3,"source_version":"WHO-MDB-ICD10-fc047e2e14694956","retrieved_at":"2026-07-22T16:07:26.508035+00:00","audit_version":"who_mortality_v1_2_2"},{"record_id":"who-mdb-014-496554ae8be44a831cac7a2b","year":2010,"sex_code":"male","death_count":0,"source_version":"WHO-MDB-ICD10-fc047e2e14694956","retrieved_at":"2026-07-22T16:07:26.508035+00:00","audit_version":"who_mortality_v1_2_2"},{"record_id":"who-mdb-014-b98c4d521ea31834f20e34b9","year":2011,"sex_code":"female","death_count":1,"source_version":"WHO-MDB-ICD10-fc047e2e14694956","retrieved_at":"2026-07-22T16:07:26.508035+00:00","audit_version":"who_mortality_v1_2_2"},{"record_id":"who-mdb-014-7ae35b8a7195e6bac68d01c3","year":2011,"sex_code":"male","death_count":2,"source_version":"WHO-MDB-ICD10-fc047e2e14694956","retrieved_at":"2026-07-22T16:07:26.508035+00:00","audit_version":"who_mortality_v1_2_2"},{"record_id":"who-mdb-014-f02b4193934657cd891f2253","year":2012,"sex_code":"female","death_count":1,"source_version":"WHO-MDB-ICD10-fc047e2e14694956","retrieved_at":"2026-07-22T16:07:26.508035+00:00","audit_version":"who_mortality_v1_2_2"},{"record_id":"who-mdb-014-36cb90a98b1e96b7c874cc3f","year":2012,"sex_code":"male","death_count":0,"source_version":"WHO-MDB-ICD10-fc047e2e14694956","retrieved_at":"2026-07-22T16:07:26.508035+00:00","audit_version":"who_mortality_v1_2_2"},{"record_id":"who-mdb-014-b4e1f5a2eb835b1c8ff0543b","year":2013,"sex_code":"female","death_count":2,"source_version":"WHO-MDB-ICD10-fc047e2e14694956","retrieved_at":"2026-07-22T16:07:26.508035+00:00","audit_version":"who_mortality_v1_2_2"},{"record_id":"who-mdb-014-0e1db48641587a4ae323135f","year":2013,"sex_code":"male","death_count":1,"source_version":"WHO-MDB-ICD10-fc047e2e14694956","retrieved_at":"2026-07-22T16:07:26.508035+00:00","audit_version":"who_mortality_v1_2_2"},{"record_id":"who-mdb-014-00e807f368bd21ee38777e27","year":2014,"sex_code":"female","death_count":0,"source_version":"WHO-MDB-ICD10-fc047e2e14694956","retrieved_at":"2026-07-22T16:07:26.508035+00:00","audit_version":"who_mortality_v1_2_2"},{"record_id":"who-mdb-014-6b4acae81bbf8414b795bd61","year":2014,"sex_code":"male","death_count":1,"source_version":"WHO-MDB-ICD10-fc047e2e14694956","retrieved_at":"2026-07-22T16:07:26.508035+00:00","audit_version":"who_mortality_v1_2_2"},{"record_id":"who-mdb-014-643a00c5bf3e51877a5f4744","year":2015,"sex_code":"female","death_count":0,"source_version":"WHO-MDB-ICD10-fc047e2e14694956","retrieved_at":"2026-07-22T16:07:26.508035+00:00","audit_version":"who_mortality_v1_2_2"},{"record_id":"who-mdb-014-caff7288f6e95aa1ff98fa83","year":2015,"sex_code":"male","death_count":1,"source_version":"WHO-MDB-ICD10-fc047e2e14694956","retrieved_at":"2026-07-22T16:07:26.508035+00:00","audit_version":"who_mortality_v1_2_2"}],"constraints":{"national_only":true,"age_scope":"under_15_partial","strict_under_18":false,"sex_aggregation":true,"source_records_sex_aggregation":false,"both_sexes_displayed_separately":true,"integrated_female_male_total":true,"integrated_total_requires_both_components":true,"integrated_total_includes_unknown":false,"unknown_sex_exposed_in_interface":false,"world_total":false,"missing_years_are_zero":false,"cross_country_comparison":true,"cross_country_sums":false,"population_rates":false}}